README.rst
setup.cfg
setup.py
src/intperm/__init__.py
src/intperm/parameters.py
src/intperm.egg-info/PKG-INFO
src/intperm.egg-info/SOURCES.txt
src/intperm.egg-info/dependency_links.txt
src/intperm.egg-info/top_level.txt
src/intperm.egg-info/zip-safe